MLImage/MLImage.py
MLImage/__init__.py
MLText/MLText.py
MLText/__init__.py
MLUtils/MLUtils.py
MLUtils/__init__.py
MLVideo/MLVideo.py
MLVideo/__init__.py
MLPlus-0.0.2.dist-info/LICENSE
MLPlus-0.0.2.dist-info/METADATA
MLPlus-0.0.2.dist-info/WHEEL
MLPlus-0.0.2.dist-info/top_level.txt
MLPlus-0.0.2.dist-info/RECORD
