Metadata-Version: 2.1
Name: MLPlus
Version: 0.0.2
Summary: Screw dataprocessing
Home-page: UNKNOWN
Author: Bugsie Segal
License: BSD
Keywords: Machine Learning
Platform: UNKNOWN
Classifier: Programming Language :: Python :: 3
Classifier: Topic :: Utilities
Classifier: License :: OSI Approved :: MIT License
Requires-Python: >=3.6
